server/__init__.py
server/run_server.py
server/common/__init__.py
server/common/decos.py
server/common/descriptors.py
server/common/errors.py
server/common/utils.py
server/common/variables.py
server/log/__init__.py
server/log/client_log_config.py
server/log/server_log_config.py
server/server/__init__.py
server/server/core.py
server/server/server_db.py
server/server/server_gui.py
server/unit_tests/__init__.py
server/unit_tests/test_utils.py
simple_mess_server-0.1.0.dist-info/METADATA
simple_mess_server-0.1.0.dist-info/WHEEL
simple_mess_server-0.1.0.dist-info/top_level.txt
simple_mess_server-0.1.0.dist-info/RECORD
